{"name":"The Bärenzwinger Font","tagline":"Baerenzwinger Font","body":"﻿Introduction:\r\n-------------\r\nThis font is inspired by old hand-made letters found in Dresden, Germany, and used is by [Studentenclub Bärenzwinger e.V.](http://baerenzwinger.de/):  \r\nhttp://postimage.org/image/hy2s2i5t1/\r\n\r\nSource code for Fontforge (http://fontforge.org/) as well as compiled font in different formats are provided:  \r\n┬ Baerenzwinger.sdf (Fontforge source file)  \r\n├ fonts_bin/  \r\n│   ├ Baerenzwinger.otf (OpenType Format)  \r\n│   ├ Baerenzwinger.svg (Scalable Vector Graphic)  \r\n│   ├ Baerenzwinger.ttf (TrueType Format)  \r\n│   └ Baerenzwinger.woff (Web Open Font Format)  \r\n└ pics/  \r\n    └ Pangramm_Baerenzwinger_Font.png  \r\n\r\nSample:\r\n-------\r\n![Sample](https://github.com/listef/Baerenzwinger_Font/pics/Pangramm_Baerenzwinger_Font.png)\r\n\r\nPlease note:\r\n------------\r\nBärenzwinger is a registered wordmark of [Studentenclub Bärenzwinger e.V.](http://baerenzwinger.de/) in Germany.\r\n\r\nLicense:\r\n--------\r\nsee [LICENSE](https://github.com/listef/Baerenzwinger_Font/LICENSE)\r\n","google":"","note":"Don't delete this file! It's used internally to help with page regeneration."}